README.txt
setup.cfg
setup.py
cs/__init__.py
cs.collage.egg-info/PKG-INFO
cs.collage.egg-info/SOURCES.txt
cs.collage.egg-info/dependency_links.txt
cs.collage.egg-info/entry_points.txt
cs.collage.egg-info/namespace_packages.txt
cs.collage.egg-info/not-zip-safe
cs.collage.egg-info/requires.txt
cs.collage.egg-info/top_level.txt
cs/collage/__init__.py
cs/collage/configure.zcml
cs/collage/tests.py
cs/collage/browser/__init__.py
cs/collage/browser/configure.zcml
cs/collage/browser/views.py
cs/collage/browser/resources/cs.collage.css
cs/collage/browser/templates/last_4_with_image.pt
cs/collage/browser/templates/last_4_with_image_for_collection.pt
cs/collage/browser/templates/row_standard.pt
cs/collage/profiles/default/cssregistry.xml
docs/HISTORY.txt
docs/INSTALL.txt
docs/LICENSE.GPL
docs/LICENSE.txt