Metadata-Version: 1.1
Name: cs.collage
Version: 1.4
Summary: UNKNOWN
Home-page: https://github.com/codesyntax/cs.collage
Author: Mikel Larreategi
Author-email: mlarreategi@codesyntax.com
License: GPL
Platform: UNKNOWN
Classifier: Framework :: Plone
Classifier: Programming Language :: Python
Classifier: Topic :: Software Development :: Libraries :: Python Modules
